easyNeuron/__init__.py
easyNeuron-0.0.1.dist-info/LICENSE
easyNeuron-0.0.1.dist-info/METADATA
easyNeuron-0.0.1.dist-info/WHEEL
easyNeuron-0.0.1.dist-info/top_level.txt
easyNeuron-0.0.1.dist-info/RECORD
