Metadata-Version: 2.1
Name: easyNeuron
Version: 0.0.1
Summary: Pure Python neural network package.
Home-page: https://github.com/Password-Classified/easyNeuron
Author: Password-Classified
Author-email: user@example.com
License: UNKNOWN
Project-URL: Bug Tracker, https://github.com/Password-Classified/easyNeuron/issues
Keywords: python,neural,networks,AI,ML,machine learning,easy,neuron,easyneuron,easyNeuron
Platform: UNKNOWN
Classifier: Development Status :: 1 - Planning
Classifier: Intended Audience :: Developers
Classifier: Programming Language :: Python :: 3
Classifier: Operating System :: Unix
Classifier: Operating System :: MacOS :: MacOS X
Classifier: Operating System :: Microsoft :: Windows
Requires-Python: >=3.6
